face_sdlr/__init__.py
face_sdlr/face.py
face_sdlr/detection/face.tflite
face_sdlr/detection/labelmap.txt
face_sdlr/detection/tflite_graph.pb
face_sdlr/detection/tflite_graph.pbtxt
face_sdlr-1.1.dist-info/METADATA
face_sdlr-1.1.dist-info/WHEEL
face_sdlr-1.1.dist-info/top_level.txt
face_sdlr-1.1.dist-info/RECORD
