Metadata-Version: 2.1
Name: face-sdlr
Version: 1.1
Summary: Face Scaling, Detection, Landmark, Recognition
Home-page: UNKNOWN
Author: Heon Je Lee
Author-email: lhjnano@gmail.com
License: MIT
Platform: UNKNOWN
Requires-Dist: sklearn (==0.0)
Requires-Dist: cmake (==3.14.4)
Requires-Dist: opencv-python (==4.4.0.46)
Requires-Dist: dlib (==19.8.1)
Requires-Dist: face-recognition (==1.3.0)
Requires-Dist: face-recognition-models
Requires-Dist: matplotlib (==3.3.2)
Requires-Dist: numpy (==1.18.5)
Requires-Dist: tensorflow (==2.2.0)
Requires-Dist: srgan-krasserm (==0.5)
